s4cmd.py
etc/bash_completion.d/s4cmd
s4cmd-2.0.1.data/scripts/s4cmd
s4cmd-2.0.1.data/scripts/s4cmd.py
s4cmd-2.0.1.dist-info/DESCRIPTION.rst
s4cmd-2.0.1.dist-info/METADATA
s4cmd-2.0.1.dist-info/RECORD
s4cmd-2.0.1.dist-info/WHEEL
s4cmd-2.0.1.dist-info/metadata.json
s4cmd-2.0.1.dist-info/top_level.txt
