Metadata-Version: 2.0
Name: s4cmd
Version: 2.0.1
Summary: Super S3 command line tool
Home-page: https://github.com/bloomreach/s4cmd
Author: Chou-han Yang
Author-email: UNKNOWN
License: http://www.apache.org/licenses/LICENSE-2.0
Platform: UNKNOWN
Requires-Dist: boto3 (>=1.3.1)
Requires-Dist: pytz (>=2016.4)
